{"InputLayer":[{"Weight":0.91077316,"Activation":0,"Bias":0.10488246,"InputNeurons":null,"OutputNeurons":null}],"HiddenLayers":[[{"Weight":0.6972819,"Activation":0,"Bias":0.3,"InputNeurons":null,"OutputNeurons":null},{"Weight":0.011222728,"Activation":0,"Bias":0.3,"InputNeurons":null,"OutputNeurons":null},{"Weight":0.6840624,"Activation":0,"Bias":0.3,"InputNeurons":null,"OutputNeurons":null},{"Weight":0.63805306,"Activation":0,"Bias":0.3,"InputNeurons":null,"OutputNeurons":null},{"Weight":0.0036351979,"Activation":0,"Bias":0.1268336,"InputNeurons":null,"OutputNeurons":null},{"Weight":0.44232517,"Activation":0,"Bias":0.3,"InputNeurons":null,"OutputNeurons":null},{"Weight":0.41751367,"Activation":0,"Bias":0.3,"InputNeurons":null,"OutputNeurons":null},{"Weight":0.48361224,"Activation":0,"Bias":0.3,"InputNeurons":null,"OutputNeurons":null},{"Weight":0.9814799,"Activation":0,"Bias":0.3,"InputNeurons":null,"OutputNeurons":null},{"Weight":0.77194464,"Activation":0,"Bias":0.3,"InputNeurons":null,"OutputNeurons":null},{"Weight":0.24011,"Activation":0,"Bias":0.207397,"InputNeurons":null,"OutputNeurons":null},{"Weight":0.23593614,"Activation":0,"Bias":0.14479528,"InputNeurons":null,"OutputNeurons":null},{"Weight":0.07814168,"Activation":0,"Bias":0.09237326,"InputNeurons":null,"OutputNeurons":null},{"Weight":0.6728948,"Activation":0,"Bias":0.1738292,"InputNeurons":null,"OutputNeurons":null},{"Weight":0.12348852,"Activation":0,"Bias":0.3,"InputNeurons":null,"OutputNeurons":null},{"Weight":0.18587284,"Activation":0,"Bias":0.3,"InputNeurons":null,"OutputNeurons":null}],[{"Weight":0.7724172,"Activation":0,"Bias":0.3,"InputNeurons":null,"OutputNeurons":null},{"Weight":0.47484985,"Activation":0,"Bias":0.3,"InputNeurons":null,"OutputNeurons":null},{"Weight":0.9344517,"Activation":0,"Bias":0.3,"InputNeurons":null,"OutputNeurons":null},{"Weight":0.84427196,"Activation":0,"Bias":0.3,"InputNeurons":null,"OutputNeurons":null},{"Weight":0.78872,"Activation":0,"Bias":0.3,"InputNeurons":null,"OutputNeurons":null},{"Weight":0.8153352,"Activation":0,"Bias":0.3,"InputNeurons":null,"OutputNeurons":null},{"Weight":0.17891803,"Activation":0,"Bias":0.3,"InputNeurons":null,"OutputNeurons":null},{"Weight":0.59868956,"Activation":0,"Bias":0.3,"InputNeurons":null,"OutputNeurons":null},{"Weight":0.06100086,"Activation":0,"Bias":0.3,"InputNeurons":null,"OutputNeurons":null},{"Weight":0.22657166,"Activation":0,"Bias":0.3,"InputNeurons":null,"OutputNeurons":null},{"Weight":0.010508279,"Activation":0,"Bias":0.28623724,"InputNeurons":null,"OutputNeurons":null},{"Weight":0.86477244,"Activation":0,"Bias":0.3,"InputNeurons":null,"OutputNeurons":null},{"Weight":0.61445665,"Activation":0,"Bias":0.3,"InputNeurons":null,"OutputNeurons":null},{"Weight":0.87084323,"Activation":0,"Bias":0.3,"InputNeurons":null,"OutputNeurons":null},{"Weight":0.9599637,"Activation":0,"Bias":0.3,"InputNeurons":null,"OutputNeurons":null},{"Weight":0.3532124,"Activation":0,"Bias":0.17608058,"InputNeurons":null,"OutputNeurons":null}]],"OuptutLayer":[null]}